{"format":"catalogTable","catalog":"sas_migration","path":"HLP_AFG_PREMIE_il_edwh","provider":"delta","writeMode":"overwrite","schema":{"type":"struct","fields":[{"name":"AFWIJKING_PREMIE_REDEN_ID","type":"double","nullable":true,"metadata":{}},{"name":"AFWIJKING_PREMIE_REDEN_CODE","type":"string","nullable":true,"metadata":{}},{"name":"AFWIJKING_PREMIE_REDEN_OMS","type":"string","nullable":true,"metadata":{}},{"name":"EDWH_PEIL_DTM","type":"date","nullable":true,"metadata":{}},{"name":"EDWH_PROCES_DTD","type":"timestamp","nullable":true,"metadata":{}},{"name":"EDWH_VERWIJDER_DTD","type":"timestamp","nullable":true,"metadata":{}},{"name":"EDWH_RESOURCE_ID","type":"double","nullable":true,"metadata":{}}]},"tableName":"afwijking_premie_reden","isCatalogEnabled":true,"componentInfo":{"gemId":"gitUri=http://gitserver:3000/XIUGo8J6_team_2/XIUGo8J6_project_4.git&subPath=&tag=0.2.25&projectSubscriptionProjectId=4&path=gems/catalogTable","projectName":"ProphecySparkBasicsPython"},"datasetType":"Database"}